sshbox/__init__.py
sshbox/json_config.py
sshbox/main.py
sshbox-0.7.2.dist-info/METADATA
sshbox-0.7.2.dist-info/WHEEL
sshbox-0.7.2.dist-info/entry_points.txt
sshbox-0.7.2.dist-info/RECORD
