Metadata-Version: 2.4
Name: sshbox
Version: 0.7.2
Summary: CLI for managing SSH connections using JSON configuration
Author-email: kwilt <kwilt@pm.me>
License: MIT
Requires-Python: >=3.12
Requires-Dist: click>=8.1.7
Requires-Dist: python-dotenv>=1.0.1
Requires-Dist: rich>=10.0.0
